setup.py
siddhis_indian_states_25/__init__.py
siddhis_indian_states_25/asgi.py
siddhis_indian_states_25/settings.py
siddhis_indian_states_25/urls.py
siddhis_indian_states_25/wsgi.py
siddhis_indian_states_25.egg-info/PKG-INFO
siddhis_indian_states_25.egg-info/SOURCES.txt
siddhis_indian_states_25.egg-info/dependency_links.txt
siddhis_indian_states_25.egg-info/requires.txt
siddhis_indian_states_25.egg-info/top_level.txt
sst2/__init__.py
sst2/admin.py
sst2/apps.py
sst2/fields.py
sst2/forms.py
sst2/models.py
sst2/states.py
sst2/tests.py
sst2/views.py
sst2/migrations/__init__.py