Metadata-Version: 2.2
Name: siddhis_indian_states_25
Version: 0.1
Summary: A Django app that provides Indian State choices as a model and form field.
Author: Siddhi Ramesh Sutar
Author-email: siddhirs2003@gmail.com
License: MIT
Classifier: Framework :: Django
Classifier: Programming Language :: Python :: 3
Requires-Dist: django
Dynamic: author
Dynamic: author-email
Dynamic: classifier
Dynamic: license
Dynamic: requires-dist
Dynamic: summary
